airflow_portainer/__init__.py
airflow_portainer/hooks/__init__.py
airflow_portainer/hooks/portainer.py
airflow_portainer/operators/__init__.py
airflow_portainer/operators/portainer.py
airflow_portainer/provider.yaml
airflow_portainer-0.1.0.dist-info/METADATA
airflow_portainer-0.1.0.dist-info/WHEEL
airflow_portainer-0.1.0.dist-info/RECORD
